{
    "actual_generations_per_production_type": [
        {
            "start_date": "2015-04-03T00:00:00+02:00",
            "end_date": "2015-04-04T00:00:00+02:00",
            "production_type": "BIOMASS",
            "values": [
                {
                    "start_date": "2015-04-03T00:00:00+02:00",
                    "end_date": "2015-04-03T01:00:00+02:00",
                    "value": 225
                },
                {
                    "start_date": "2015-04-03T01:00:00+02:00",
                    "end_date": "2015-04-03T02:00:00+02:00",
                    "value": 225
                },
                {
                    "start_date": "2015-04-03T02:00:00+02:00",
                    "end_date": "2015-04-03T03:00:00+02:00",
                    "value": 225
                },
                {
                    "start_date": "2015-04-03T03:00:00+02:00",
                    "end_date": "2015-04-03T04:00:00+02:00",
                    "value": 225
                },
                {
                    "start_date": "2015-04-03T04:00:00+02:00",
                    "end_date": "2015-04-03T05:00:00+02:00",
                    "value": 225
                },
                {
                    "start_date": "2015-04-03T05:00:00+02:00",
                    "end_date": "2015-04-03T06:00:00+02:00",
                    "value": 225
                },
                {
                    "start_date": "2015-04-03T06:00:00+02:00",
                    "end_date": "2015-04-03T07:00:00+02:00",
                    "value": 225
                },
                {
                    "start_date": "2015-04-03T07:00:00+02:00",
                    "end_date": "2015-04-03T08:00:00+02:00",
                    "value": 225
                },
                {
                    "start_date": "2015-04-03T08:00:00+02:00",
                    "end_date": "2015-04-03T09:00:00+02:00",
                    "value": 225
                },
                {
                    "start_date": "2015-04-03T09:00:00+02:00",
                    "end_date": "2015-04-03T10:00:00+02:00",
                    "value": 225
                },
                {
                    "start_date": "2015-04-03T10:00:00+02:00",
                    "end_date": "2015-04-03T11:00:00+02:00",
                    "value": 225
                },
                {
                    "start_date": "2015-04-03T11:00:00+02:00",
                    "end_date": "2015-04-03T12:00:00+02:00",
                    "value": 225
                },
                {
                    "start_date": "2015-04-03T12:00:00+02:00",
                    "end_date": "2015-04-03T13:00:00+02:00",
                    "value": 225
                },
                {
                    "start_date": "2015-04-03T13:00:00+02:00",
                    "end_date": "2015-04-03T14:00:00+02:00",
                    "value": 225
                },
                {
                    "start_date": "2015-04-03T14:00:00+02:00",
                    "end_date": "2015-04-03T15:00:00+02:00",
                    "value": 225
                },
                {
                    "start_date": "2015-04-03T15:00:00+02:00",
                    "end_date": "2015-04-03T16:00:00+02:00",
                    "value": 225
                },
                {
                    "start_date": "2015-04-03T16:00:00+02:00",
                    "end_date": "2015-04-03T17:00:00+02:00",
                    "value": 225
                },
                {
                    "start_date": "2015-04-03T17:00:00+02:00",
                    "end_date": "2015-04-03T18:00:00+02:00",
                    "value": 224
                },
                {
                    "start_date": "2015-04-03T18:00:00+02:00",
                    "end_date": "2015-04-03T19:00:00+02:00",
                    "value": 224
                },
                {
                    "start_date": "2015-04-03T19:00:00+02:00",
                    "end_date": "2015-04-03T20:00:00+02:00",
                    "value": 224
                },
                {
                    "start_date": "2015-04-03T20:00:00+02:00",
                    "end_date": "2015-04-03T21:00:00+02:00",
                    "value": 223
                },
                {
                    "start_date": "2015-04-03T21:00:00+02:00",
                    "end_date": "2015-04-03T22:00:00+02:00",
                    "value": 223
                },
                {
                    "start_date": "2015-04-03T22:00:00+02:00",
                    "end_date": "2015-04-03T23:00:00+02:00",
                    "value": 223
                },
                {
                    "start_date": "2015-04-03T23:00:00+02:00",
                    "end_date": "2015-04-04T00:00:00+02:00",
                    "value": 224
                }
            ]
        },
        {
            "start_date": "2015-04-03T00:00:00+02:00",
            "end_date": "2015-04-04T00:00:00+02:00",
            "production_type": "FOSSIL_GAS",
            "values": [
                {
                    "start_date": "2015-04-03T00:00:00+02:00",
                    "end_date": "2015-04-03T01:00:00+02:00",
                    "value": 2269
                },
                {
                    "start_date": "2015-04-03T01:00:00+02:00",
                    "end_date": "2015-04-03T02:00:00+02:00",
                    "value": 1871
                },
                {
                    "start_date": "2015-04-03T02:00:00+02:00",
                    "end_date": "2015-04-03T03:00:00+02:00",
                    "value": 1765
                },
                {
                    "start_date": "2015-04-03T03:00:00+02:00",
                    "end_date": "2015-04-03T04:00:00+02:00",
                    "value": 1571
                },
                {
                    "start_date": "2015-04-03T04:00:00+02:00",
                    "end_date": "2015-04-03T05:00:00+02:00",
                    "value": 1555
                },
                {
                    "start_date": "2015-04-03T05:00:00+02:00",
                    "end_date": "2015-04-03T06:00:00+02:00",
                    "value": 1632
                },
                {
                    "start_date": "2015-04-03T06:00:00+02:00",
                    "end_date": "2015-04-03T07:00:00+02:00",
                    "value": 2031
                },
                {
                    "start_date": "2015-04-03T07:00:00+02:00",
                    "end_date": "2015-04-03T08:00:00+02:00",
                    "value": 2567
                },
                {
                    "start_date": "2015-04-03T08:00:00+02:00",
                    "end_date": "2015-04-03T09:00:00+02:00",
                    "value": 2693
                },
                {
                    "start_date": "2015-04-03T09:00:00+02:00",
                    "end_date": "2015-04-03T10:00:00+02:00",
                    "value": 2734
                },
                {
                    "start_date": "2015-04-03T10:00:00+02:00",
                    "end_date": "2015-04-03T11:00:00+02:00",
                    "value": 2735
                },
                {
                    "start_date": "2015-04-03T11:00:00+02:00",
                    "end_date": "2015-04-03T12:00:00+02:00",
                    "value": 2729
                },
                {
                    "start_date": "2015-04-03T12:00:00+02:00",
                    "end_date": "2015-04-03T13:00:00+02:00",
                    "value": 2665
                },
                {
                    "start_date": "2015-04-03T13:00:00+02:00",
                    "end_date": "2015-04-03T14:00:00+02:00",
                    "value": 2226
                },
                {
                    "start_date": "2015-04-03T14:00:00+02:00",
                    "end_date": "2015-04-03T15:00:00+02:00",
                    "value": 1722
                },
                {
                    "start_date": "2015-04-03T15:00:00+02:00",
                    "end_date": "2015-04-03T16:00:00+02:00",
                    "value": 1735
                },
                {
                    "start_date": "2015-04-03T16:00:00+02:00",
                    "end_date": "2015-04-03T17:00:00+02:00",
                    "value": 1710
                },
                {
                    "start_date": "2015-04-03T17:00:00+02:00",
                    "end_date": "2015-04-03T18:00:00+02:00",
                    "value": 1738
                },
                {
                    "start_date": "2015-04-03T18:00:00+02:00",
                    "end_date": "2015-04-03T19:00:00+02:00",
                    "value": 1769
                },
                {
                    "start_date": "2015-04-03T19:00:00+02:00",
                    "end_date": "2015-04-03T20:00:00+02:00",
                    "value": 1767
                },
                {
                    "start_date": "2015-04-03T20:00:00+02:00",
                    "end_date": "2015-04-03T21:00:00+02:00",
                    "value": 1734
                },
                {
                    "start_date": "2015-04-03T21:00:00+02:00",
                    "end_date": "2015-04-03T22:00:00+02:00",
                    "value": 1688
                },
                {
                    "start_date": "2015-04-03T22:00:00+02:00",
                    "end_date": "2015-04-03T23:00:00+02:00",
                    "value": 1544
                },
                {
                    "start_date": "2015-04-03T23:00:00+02:00",
                    "end_date": "2015-04-04T00:00:00+02:00",
                    "value": 1475
                }
            ]
        },
        {
            "start_date": "2015-04-03T00:00:00+02:00",
            "end_date": "2015-04-04T00:00:00+02:00",
            "production_type": "FOSSIL_HARD_COAL",
            "values": [
                {
                    "start_date": "2015-04-03T00:00:00+02:00",
                    "end_date": "2015-04-03T01:00:00+02:00",
                    "value": 644
                },
                {
                    "start_date": "2015-04-03T01:00:00+02:00",
                    "end_date": "2015-04-03T02:00:00+02:00",
                    "value": 289
                },
                {
                    "start_date": "2015-04-03T02:00:00+02:00",
                    "end_date": "2015-04-03T03:00:00+02:00",
                    "value": 289
                },
                {
                    "start_date": "2015-04-03T03:00:00+02:00",
                    "end_date": "2015-04-03T04:00:00+02:00",
                    "value": 279
                },
                {
                    "start_date": "2015-04-03T04:00:00+02:00",
                    "end_date": "2015-04-03T05:00:00+02:00",
                    "value": 274
                },
                {
                    "start_date": "2015-04-03T05:00:00+02:00",
                    "end_date": "2015-04-03T06:00:00+02:00",
                    "value": 253
                },
                {
                    "start_date": "2015-04-03T06:00:00+02:00",
                    "end_date": "2015-04-03T07:00:00+02:00",
                    "value": 257
                },
                {
                    "start_date": "2015-04-03T07:00:00+02:00",
                    "end_date": "2015-04-03T08:00:00+02:00",
                    "value": 251
                },
                {
                    "start_date": "2015-04-03T08:00:00+02:00",
                    "end_date": "2015-04-03T09:00:00+02:00",
                    "value": 256
                },
                {
                    "start_date": "2015-04-03T09:00:00+02:00",
                    "end_date": "2015-04-03T10:00:00+02:00",
                    "value": 256
                },
                {
                    "start_date": "2015-04-03T10:00:00+02:00",
                    "end_date": "2015-04-03T11:00:00+02:00",
                    "value": 265
                },
                {
                    "start_date": "2015-04-03T11:00:00+02:00",
                    "end_date": "2015-04-03T12:00:00+02:00",
                    "value": 214
                },
                {
                    "start_date": "2015-04-03T12:00:00+02:00",
                    "end_date": "2015-04-03T13:00:00+02:00",
                    "value": 122
                },
                {
                    "start_date": "2015-04-03T13:00:00+02:00",
                    "end_date": "2015-04-03T14:00:00+02:00",
                    "value": 124
                },
                {
                    "start_date": "2015-04-03T14:00:00+02:00",
                    "end_date": "2015-04-03T15:00:00+02:00",
                    "value": 128
                },
                {
                    "start_date": "2015-04-03T15:00:00+02:00",
                    "end_date": "2015-04-03T16:00:00+02:00",
                    "value": 143
                },
                {
                    "start_date": "2015-04-03T16:00:00+02:00",
                    "end_date": "2015-04-03T17:00:00+02:00",
                    "value": 218
                },
                {
                    "start_date": "2015-04-03T17:00:00+02:00",
                    "end_date": "2015-04-03T18:00:00+02:00",
                    "value": 269
                },
                {
                    "start_date": "2015-04-03T18:00:00+02:00",
                    "end_date": "2015-04-03T19:00:00+02:00",
                    "value": 355
                },
                {
                    "start_date": "2015-04-03T19:00:00+02:00",
                    "end_date": "2015-04-03T20:00:00+02:00",
                    "value": 362
                },
                {
                    "start_date": "2015-04-03T20:00:00+02:00",
                    "end_date": "2015-04-03T21:00:00+02:00",
                    "value": 419
                },
                {
                    "start_date": "2015-04-03T21:00:00+02:00",
                    "end_date": "2015-04-03T22:00:00+02:00",
                    "value": 453
                },
                {
                    "start_date": "2015-04-03T22:00:00+02:00",
                    "end_date": "2015-04-03T23:00:00+02:00",
                    "value": 454
                },
                {
                    "start_date": "2015-04-03T23:00:00+02:00",
                    "end_date": "2015-04-04T00:00:00+02:00",
                    "value": 453
                }
            ]
        },
        {
            "start_date": "2015-04-03T00:00:00+02:00",
            "end_date": "2015-04-04T00:00:00+02:00",
            "production_type": "FOSSIL_OIL",
            "values": [
                {
                    "start_date": "2015-04-03T00:00:00+02:00",
                    "end_date": "2015-04-03T01:00:00+02:00",
                    "value": 278
                },
                {
                    "start_date": "2015-04-03T01:00:00+02:00",
                    "end_date": "2015-04-03T02:00:00+02:00",
                    "value": 279
                },
                {
                    "start_date": "2015-04-03T02:00:00+02:00",
                    "end_date": "2015-04-03T03:00:00+02:00",
                    "value": 278
                },
                {
                    "start_date": "2015-04-03T03:00:00+02:00",
                    "end_date": "2015-04-03T04:00:00+02:00",
                    "value": 277
                },
                {
                    "start_date": "2015-04-03T04:00:00+02:00",
                    "end_date": "2015-04-03T05:00:00+02:00",
                    "value": 278
                },
                {
                    "start_date": "2015-04-03T05:00:00+02:00",
                    "end_date": "2015-04-03T06:00:00+02:00",
                    "value": 278
                },
                {
                    "start_date": "2015-04-03T06:00:00+02:00",
                    "end_date": "2015-04-03T07:00:00+02:00",
                    "value": 280
                },
                {
                    "start_date": "2015-04-03T07:00:00+02:00",
                    "end_date": "2015-04-03T08:00:00+02:00",
                    "value": 279
                },
                {
                    "start_date": "2015-04-03T08:00:00+02:00",
                    "end_date": "2015-04-03T09:00:00+02:00",
                    "value": 279
                },
                {
                    "start_date": "2015-04-03T09:00:00+02:00",
                    "end_date": "2015-04-03T10:00:00+02:00",
                    "value": 278
                },
                {
                    "start_date": "2015-04-03T10:00:00+02:00",
                    "end_date": "2015-04-03T11:00:00+02:00",
                    "value": 279
                },
                {
                    "start_date": "2015-04-03T11:00:00+02:00",
                    "end_date": "2015-04-03T12:00:00+02:00",
                    "value": 279
                },
                {
                    "start_date": "2015-04-03T12:00:00+02:00",
                    "end_date": "2015-04-03T13:00:00+02:00",
                    "value": 279
                },
                {
                    "start_date": "2015-04-03T13:00:00+02:00",
                    "end_date": "2015-04-03T14:00:00+02:00",
                    "value": 279
                },
                {
                    "start_date": "2015-04-03T14:00:00+02:00",
                    "end_date": "2015-04-03T15:00:00+02:00",
                    "value": 279
                },
                {
                    "start_date": "2015-04-03T15:00:00+02:00",
                    "end_date": "2015-04-03T16:00:00+02:00",
                    "value": 279
                },
                {
                    "start_date": "2015-04-03T16:00:00+02:00",
                    "end_date": "2015-04-03T17:00:00+02:00",
                    "value": 279
                },
                {
                    "start_date": "2015-04-03T17:00:00+02:00",
                    "end_date": "2015-04-03T18:00:00+02:00",
                    "value": 279
                },
                {
                    "start_date": "2015-04-03T18:00:00+02:00",
                    "end_date": "2015-04-03T19:00:00+02:00",
                    "value": 279
                },
                {
                    "start_date": "2015-04-03T19:00:00+02:00",
                    "end_date": "2015-04-03T20:00:00+02:00",
                    "value": 280
                },
                {
                    "start_date": "2015-04-03T20:00:00+02:00",
                    "end_date": "2015-04-03T21:00:00+02:00",
                    "value": 278
                },
                {
                    "start_date": "2015-04-03T21:00:00+02:00",
                    "end_date": "2015-04-03T22:00:00+02:00",
                    "value": 278
                },
                {
                    "start_date": "2015-04-03T22:00:00+02:00",
                    "end_date": "2015-04-03T23:00:00+02:00",
                    "value": 280
                },
                {
                    "start_date": "2015-04-03T23:00:00+02:00",
                    "end_date": "2015-04-04T00:00:00+02:00",
                    "value": 278
                }
            ]
        },
        {
            "start_date": "2015-04-03T00:00:00+02:00",
            "end_date": "2015-04-04T00:00:00+02:00",
            "production_type": "HYDRO_PUMPED_STORAGE",
            "values": [
                {
                    "start_date": "2015-04-03T00:00:00+02:00",
                    "end_date": "2015-04-03T01:00:00+02:00",
                    "value": 282
                },
                {
                    "start_date": "2015-04-03T01:00:00+02:00",
                    "end_date": "2015-04-03T02:00:00+02:00",
                    "value": -817
                },
                {
                    "start_date": "2015-04-03T02:00:00+02:00",
                    "end_date": "2015-04-03T03:00:00+02:00",
                    "value": -1706
                },
                {
                    "start_date": "2015-04-03T03:00:00+02:00",
                    "end_date": "2015-04-03T04:00:00+02:00",
                    "value": -2489
                },
                {
                    "start_date": "2015-04-03T04:00:00+02:00",
                    "end_date": "2015-04-03T05:00:00+02:00",
                    "value": -2484
                },
                {
                    "start_date": "2015-04-03T05:00:00+02:00",
                    "end_date": "2015-04-03T06:00:00+02:00",
                    "value": -2016
                },
                {
                    "start_date": "2015-04-03T06:00:00+02:00",
                    "end_date": "2015-04-03T07:00:00+02:00",
                    "value": -746
                },
                {
                    "start_date": "2015-04-03T07:00:00+02:00",
                    "end_date": "2015-04-03T08:00:00+02:00",
                    "value": 782
                },
                {
                    "start_date": "2015-04-03T08:00:00+02:00",
                    "end_date": "2015-04-03T09:00:00+02:00",
                    "value": 638
                },
                {
                    "start_date": "2015-04-03T09:00:00+02:00",
                    "end_date": "2015-04-03T10:00:00+02:00",
                    "value": 1034
                },
                {
                    "start_date": "2015-04-03T10:00:00+02:00",
                    "end_date": "2015-04-03T11:00:00+02:00",
                    "value": 815
                },
                {
                    "start_date": "2015-04-03T11:00:00+02:00",
                    "end_date": "2015-04-03T12:00:00+02:00",
                    "value": 732
                },
                {
                    "start_date": "2015-04-03T12:00:00+02:00",
                    "end_date": "2015-04-03T13:00:00+02:00",
                    "value": 637
                },
                {
                    "start_date": "2015-04-03T13:00:00+02:00",
                    "end_date": "2015-04-03T14:00:00+02:00",
                    "value": 356
                },
                {
                    "start_date": "2015-04-03T14:00:00+02:00",
                    "end_date": "2015-04-03T15:00:00+02:00",
                    "value": 53
                },
                {
                    "start_date": "2015-04-03T15:00:00+02:00",
                    "end_date": "2015-04-03T16:00:00+02:00",
                    "value": -106
                },
                {
                    "start_date": "2015-04-03T16:00:00+02:00",
                    "end_date": "2015-04-03T17:00:00+02:00",
                    "value": -713
                },
                {
                    "start_date": "2015-04-03T17:00:00+02:00",
                    "end_date": "2015-04-03T18:00:00+02:00",
                    "value": 45
                },
                {
                    "start_date": "2015-04-03T18:00:00+02:00",
                    "end_date": "2015-04-03T19:00:00+02:00",
                    "value": 283
                },
                {
                    "start_date": "2015-04-03T19:00:00+02:00",
                    "end_date": "2015-04-03T20:00:00+02:00",
                    "value": 636
                },
                {
                    "start_date": "2015-04-03T20:00:00+02:00",
                    "end_date": "2015-04-03T21:00:00+02:00",
                    "value": 368
                },
                {
                    "start_date": "2015-04-03T21:00:00+02:00",
                    "end_date": "2015-04-03T22:00:00+02:00",
                    "value": -116
                },
                {
                    "start_date": "2015-04-03T22:00:00+02:00",
                    "end_date": "2015-04-03T23:00:00+02:00",
                    "value": -195
                },
                {
                    "start_date": "2015-04-03T23:00:00+02:00",
                    "end_date": "2015-04-04T00:00:00+02:00",
                    "value": 511
                }
            ]
        },
        {
            "start_date": "2015-04-03T00:00:00+02:00",
            "end_date": "2015-04-04T00:00:00+02:00",
            "production_type": "HYDRO_RUN_OF_RIVER_AND_POUNDAGE",
            "values": [
                {
                    "start_date": "2015-04-03T00:00:00+02:00",
                    "end_date": "2015-04-03T01:00:00+02:00",
                    "value": 6654
                },
                {
                    "start_date": "2015-04-03T01:00:00+02:00",
                    "end_date": "2015-04-03T02:00:00+02:00",
                    "value": 6485
                },
                {
                    "start_date": "2015-04-03T02:00:00+02:00",
                    "end_date": "2015-04-03T03:00:00+02:00",
                    "value": 6455
                },
                {
                    "start_date": "2015-04-03T03:00:00+02:00",
                    "end_date": "2015-04-03T04:00:00+02:00",
                    "value": 6400
                },
                {
                    "start_date": "2015-04-03T04:00:00+02:00",
                    "end_date": "2015-04-03T05:00:00+02:00",
                    "value": 6309
                },
                {
                    "start_date": "2015-04-03T05:00:00+02:00",
                    "end_date": "2015-04-03T06:00:00+02:00",
                    "value": 6384
                },
                {
                    "start_date": "2015-04-03T06:00:00+02:00",
                    "end_date": "2015-04-03T07:00:00+02:00",
                    "value": 6498
                },
                {
                    "start_date": "2015-04-03T07:00:00+02:00",
                    "end_date": "2015-04-03T08:00:00+02:00",
                    "value": 6766
                },
                {
                    "start_date": "2015-04-03T08:00:00+02:00",
                    "end_date": "2015-04-03T09:00:00+02:00",
                    "value": 6913
                },
                {
                    "start_date": "2015-04-03T09:00:00+02:00",
                    "end_date": "2015-04-03T10:00:00+02:00",
                    "value": 6974
                },
                {
                    "start_date": "2015-04-03T10:00:00+02:00",
                    "end_date": "2015-04-03T11:00:00+02:00",
                    "value": 6919
                },
                {
                    "start_date": "2015-04-03T11:00:00+02:00",
                    "end_date": "2015-04-03T12:00:00+02:00",
                    "value": 7085
                },
                {
                    "start_date": "2015-04-03T12:00:00+02:00",
                    "end_date": "2015-04-03T13:00:00+02:00",
                    "value": 7028
                },
                {
                    "start_date": "2015-04-03T13:00:00+02:00",
                    "end_date": "2015-04-03T14:00:00+02:00",
                    "value": 6947
                },
                {
                    "start_date": "2015-04-03T14:00:00+02:00",
                    "end_date": "2015-04-03T15:00:00+02:00",
                    "value": 6749
                },
                {
                    "start_date": "2015-04-03T15:00:00+02:00",
                    "end_date": "2015-04-03T16:00:00+02:00",
                    "value": 6647
                },
                {
                    "start_date": "2015-04-03T16:00:00+02:00",
                    "end_date": "2015-04-03T17:00:00+02:00",
                    "value": 6583
                },
                {
                    "start_date": "2015-04-03T17:00:00+02:00",
                    "end_date": "2015-04-03T18:00:00+02:00",
                    "value": 6610
                },
                {
                    "start_date": "2015-04-03T18:00:00+02:00",
                    "end_date": "2015-04-03T19:00:00+02:00",
                    "value": 6865
                },
                {
                    "start_date": "2015-04-03T19:00:00+02:00",
                    "end_date": "2015-04-03T20:00:00+02:00",
                    "value": 7085
                },
                {
                    "start_date": "2015-04-03T20:00:00+02:00",
                    "end_date": "2015-04-03T21:00:00+02:00",
                    "value": 7032
                },
                {
                    "start_date": "2015-04-03T21:00:00+02:00",
                    "end_date": "2015-04-03T22:00:00+02:00",
                    "value": 6928
                },
                {
                    "start_date": "2015-04-03T22:00:00+02:00",
                    "end_date": "2015-04-03T23:00:00+02:00",
                    "value": 6930
                },
                {
                    "start_date": "2015-04-03T23:00:00+02:00",
                    "end_date": "2015-04-04T00:00:00+02:00",
                    "value": 6946
                }
            ]
        },
        {
            "start_date": "2015-04-03T00:00:00+02:00",
            "end_date": "2015-04-04T00:00:00+02:00",
            "production_type": "HYDRO_WATER_RESERVOIR",
            "values": [
                {
                    "start_date": "2015-04-03T00:00:00+02:00",
                    "end_date": "2015-04-03T01:00:00+02:00",
                    "value": 1596
                },
                {
                    "start_date": "2015-04-03T01:00:00+02:00",
                    "end_date": "2015-04-03T02:00:00+02:00",
                    "value": 1234
                },
                {
                    "start_date": "2015-04-03T02:00:00+02:00",
                    "end_date": "2015-04-03T03:00:00+02:00",
                    "value": 1127
                },
                {
                    "start_date": "2015-04-03T03:00:00+02:00",
                    "end_date": "2015-04-03T04:00:00+02:00",
                    "value": 1032
                },
                {
                    "start_date": "2015-04-03T04:00:00+02:00",
                    "end_date": "2015-04-03T05:00:00+02:00",
                    "value": 1007
                },
                {
                    "start_date": "2015-04-03T05:00:00+02:00",
                    "end_date": "2015-04-03T06:00:00+02:00",
                    "value": 868
                },
                {
                    "start_date": "2015-04-03T06:00:00+02:00",
                    "end_date": "2015-04-03T07:00:00+02:00",
                    "value": 1064
                },
                {
                    "start_date": "2015-04-03T07:00:00+02:00",
                    "end_date": "2015-04-03T08:00:00+02:00",
                    "value": 2931
                },
                {
                    "start_date": "2015-04-03T08:00:00+02:00",
                    "end_date": "2015-04-03T09:00:00+02:00",
                    "value": 3260
                },
                {
                    "start_date": "2015-04-03T09:00:00+02:00",
                    "end_date": "2015-04-03T10:00:00+02:00",
                    "value": 3312
                },
                {
                    "start_date": "2015-04-03T10:00:00+02:00",
                    "end_date": "2015-04-03T11:00:00+02:00",
                    "value": 3076
                },
                {
                    "start_date": "2015-04-03T11:00:00+02:00",
                    "end_date": "2015-04-03T12:00:00+02:00",
                    "value": 3082
                },
                {
                    "start_date": "2015-04-03T12:00:00+02:00",
                    "end_date": "2015-04-03T13:00:00+02:00",
                    "value": 2991
                },
                {
                    "start_date": "2015-04-03T13:00:00+02:00",
                    "end_date": "2015-04-03T14:00:00+02:00",
                    "value": 2761
                },
                {
                    "start_date": "2015-04-03T14:00:00+02:00",
                    "end_date": "2015-04-03T15:00:00+02:00",
                    "value": 2618
                },
                {
                    "start_date": "2015-04-03T15:00:00+02:00",
                    "end_date": "2015-04-03T16:00:00+02:00",
                    "value": 2243
                },
                {
                    "start_date": "2015-04-03T16:00:00+02:00",
                    "end_date": "2015-04-03T17:00:00+02:00",
                    "value": 2242
                },
                {
                    "start_date": "2015-04-03T17:00:00+02:00",
                    "end_date": "2015-04-03T18:00:00+02:00",
                    "value": 1969
                },
                {
                    "start_date": "2015-04-03T18:00:00+02:00",
                    "end_date": "2015-04-03T19:00:00+02:00",
                    "value": 2863
                },
                {
                    "start_date": "2015-04-03T19:00:00+02:00",
                    "end_date": "2015-04-03T20:00:00+02:00",
                    "value": 3063
                },
                {
                    "start_date": "2015-04-03T20:00:00+02:00",
                    "end_date": "2015-04-03T21:00:00+02:00",
                    "value": 2888
                },
                {
                    "start_date": "2015-04-03T21:00:00+02:00",
                    "end_date": "2015-04-03T22:00:00+02:00",
                    "value": 2150
                },
                {
                    "start_date": "2015-04-03T22:00:00+02:00",
                    "end_date": "2015-04-03T23:00:00+02:00",
                    "value": 2466
                },
                {
                    "start_date": "2015-04-03T23:00:00+02:00",
                    "end_date": "2015-04-04T00:00:00+02:00",
                    "value": 3732
                }
            ]
        },
        {
            "start_date": "2015-04-03T00:00:00+02:00",
            "end_date": "2015-04-04T00:00:00+02:00",
            "production_type": "NUCLEAR",
            "values": [
                {
                    "start_date": "2015-04-03T00:00:00+02:00",
                    "end_date": "2015-04-03T01:00:00+02:00",
                    "value": 47275
                },
                {
                    "start_date": "2015-04-03T01:00:00+02:00",
                    "end_date": "2015-04-03T02:00:00+02:00",
                    "value": 47066
                },
                {
                    "start_date": "2015-04-03T02:00:00+02:00",
                    "end_date": "2015-04-03T03:00:00+02:00",
                    "value": 46817
                },
                {
                    "start_date": "2015-04-03T03:00:00+02:00",
                    "end_date": "2015-04-03T04:00:00+02:00",
                    "value": 46458
                },
                {
                    "start_date": "2015-04-03T04:00:00+02:00",
                    "end_date": "2015-04-03T05:00:00+02:00",
                    "value": 46444
                },
                {
                    "start_date": "2015-04-03T05:00:00+02:00",
                    "end_date": "2015-04-03T06:00:00+02:00",
                    "value": 46371
                },
                {
                    "start_date": "2015-04-03T06:00:00+02:00",
                    "end_date": "2015-04-03T07:00:00+02:00",
                    "value": 47042
                },
                {
                    "start_date": "2015-04-03T07:00:00+02:00",
                    "end_date": "2015-04-03T08:00:00+02:00",
                    "value": 47430
                },
                {
                    "start_date": "2015-04-03T08:00:00+02:00",
                    "end_date": "2015-04-03T09:00:00+02:00",
                    "value": 47916
                },
                {
                    "start_date": "2015-04-03T09:00:00+02:00",
                    "end_date": "2015-04-03T10:00:00+02:00",
                    "value": 47917
                },
                {
                    "start_date": "2015-04-03T10:00:00+02:00",
                    "end_date": "2015-04-03T11:00:00+02:00",
                    "value": 47905
                },
                {
                    "start_date": "2015-04-03T11:00:00+02:00",
                    "end_date": "2015-04-03T12:00:00+02:00",
                    "value": 47829
                },
                {
                    "start_date": "2015-04-03T12:00:00+02:00",
                    "end_date": "2015-04-03T13:00:00+02:00",
                    "value": 47860
                },
                {
                    "start_date": "2015-04-03T13:00:00+02:00",
                    "end_date": "2015-04-03T14:00:00+02:00",
                    "value": 47686
                },
                {
                    "start_date": "2015-04-03T14:00:00+02:00",
                    "end_date": "2015-04-03T15:00:00+02:00",
                    "value": 47633
                },
                {
                    "start_date": "2015-04-03T15:00:00+02:00",
                    "end_date": "2015-04-03T16:00:00+02:00",
                    "value": 47462
                },
                {
                    "start_date": "2015-04-03T16:00:00+02:00",
                    "end_date": "2015-04-03T17:00:00+02:00",
                    "value": 47360
                },
                {
                    "start_date": "2015-04-03T17:00:00+02:00",
                    "end_date": "2015-04-03T18:00:00+02:00",
                    "value": 47457
                },
                {
                    "start_date": "2015-04-03T18:00:00+02:00",
                    "end_date": "2015-04-03T19:00:00+02:00",
                    "value": 47624
                },
                {
                    "start_date": "2015-04-03T19:00:00+02:00",
                    "end_date": "2015-04-03T20:00:00+02:00",
                    "value": 47848
                },
                {
                    "start_date": "2015-04-03T20:00:00+02:00",
                    "end_date": "2015-04-03T21:00:00+02:00",
                    "value": 47911
                },
                {
                    "start_date": "2015-04-03T21:00:00+02:00",
                    "end_date": "2015-04-03T22:00:00+02:00",
                    "value": 47749
                },
                {
                    "start_date": "2015-04-03T22:00:00+02:00",
                    "end_date": "2015-04-03T23:00:00+02:00",
                    "value": 46784
                },
                {
                    "start_date": "2015-04-03T23:00:00+02:00",
                    "end_date": "2015-04-04T00:00:00+02:00",
                    "value": 45507
                }
            ]
        },
        {
            "start_date": "2015-04-03T00:00:00+02:00",
            "end_date": "2015-04-04T00:00:00+02:00",
            "production_type": "SOLAR",
            "values": [
                {
                    "start_date": "2015-04-03T00:00:00+02:00",
                    "end_date": "2015-04-03T01:00:00+02:00",
                    "value": 0
                },
                {
                    "start_date": "2015-04-03T01:00:00+02:00",
                    "end_date": "2015-04-03T02:00:00+02:00",
                    "value": 0
                },
                {
                    "start_date": "2015-04-03T02:00:00+02:00",
                    "end_date": "2015-04-03T03:00:00+02:00",
                    "value": 0
                },
                {
                    "start_date": "2015-04-03T03:00:00+02:00",
                    "end_date": "2015-04-03T04:00:00+02:00",
                    "value": 0
                },
                {
                    "start_date": "2015-04-03T04:00:00+02:00",
                    "end_date": "2015-04-03T05:00:00+02:00",
                    "value": 0
                },
                {
                    "start_date": "2015-04-03T05:00:00+02:00",
                    "end_date": "2015-04-03T06:00:00+02:00",
                    "value": 0
                },
                {
                    "start_date": "2015-04-03T06:00:00+02:00",
                    "end_date": "2015-04-03T07:00:00+02:00",
                    "value": 21
                },
                {
                    "start_date": "2015-04-03T07:00:00+02:00",
                    "end_date": "2015-04-03T08:00:00+02:00",
                    "value": 72
                },
                {
                    "start_date": "2015-04-03T08:00:00+02:00",
                    "end_date": "2015-04-03T09:00:00+02:00",
                    "value": 384
                },
                {
                    "start_date": "2015-04-03T09:00:00+02:00",
                    "end_date": "2015-04-03T10:00:00+02:00",
                    "value": 988
                },
                {
                    "start_date": "2015-04-03T10:00:00+02:00",
                    "end_date": "2015-04-03T11:00:00+02:00",
                    "value": 1540
                },
                {
                    "start_date": "2015-04-03T11:00:00+02:00",
                    "end_date": "2015-04-03T12:00:00+02:00",
                    "value": 1968
                },
                {
                    "start_date": "2015-04-03T12:00:00+02:00",
                    "end_date": "2015-04-03T13:00:00+02:00",
                    "value": 2227
                },
                {
                    "start_date": "2015-04-03T13:00:00+02:00",
                    "end_date": "2015-04-03T14:00:00+02:00",
                    "value": 2361
                },
                {
                    "start_date": "2015-04-03T14:00:00+02:00",
                    "end_date": "2015-04-03T15:00:00+02:00",
                    "value": 2393
                },
                {
                    "start_date": "2015-04-03T15:00:00+02:00",
                    "end_date": "2015-04-03T16:00:00+02:00",
                    "value": 2220
                },
                {
                    "start_date": "2015-04-03T16:00:00+02:00",
                    "end_date": "2015-04-03T17:00:00+02:00",
                    "value": 1880
                },
                {
                    "start_date": "2015-04-03T17:00:00+02:00",
                    "end_date": "2015-04-03T18:00:00+02:00",
                    "value": 1312
                },
                {
                    "start_date": "2015-04-03T18:00:00+02:00",
                    "end_date": "2015-04-03T19:00:00+02:00",
                    "value": 675
                },
                {
                    "start_date": "2015-04-03T19:00:00+02:00",
                    "end_date": "2015-04-03T20:00:00+02:00",
                    "value": 199
                },
                {
                    "start_date": "2015-04-03T20:00:00+02:00",
                    "end_date": "2015-04-03T21:00:00+02:00",
                    "value": 0
                },
                {
                    "start_date": "2015-04-03T21:00:00+02:00",
                    "end_date": "2015-04-03T22:00:00+02:00",
                    "value": 0
                },
                {
                    "start_date": "2015-04-03T22:00:00+02:00",
                    "end_date": "2015-04-03T23:00:00+02:00",
                    "value": 0
                },
                {
                    "start_date": "2015-04-03T23:00:00+02:00",
                    "end_date": "2015-04-04T00:00:00+02:00",
                    "value": 0
                }
            ]
        },
        {
            "start_date": "2015-04-03T00:00:00+02:00",
            "end_date": "2015-04-04T00:00:00+02:00",
            "production_type": "WASTE",
            "values": [
                {
                    "start_date": "2015-04-03T00:00:00+02:00",
                    "end_date": "2015-04-03T01:00:00+02:00",
                    "value": 214
                },
                {
                    "start_date": "2015-04-03T01:00:00+02:00",
                    "end_date": "2015-04-03T02:00:00+02:00",
                    "value": 215
                },
                {
                    "start_date": "2015-04-03T02:00:00+02:00",
                    "end_date": "2015-04-03T03:00:00+02:00",
                    "value": 218
                },
                {
                    "start_date": "2015-04-03T03:00:00+02:00",
                    "end_date": "2015-04-03T04:00:00+02:00",
                    "value": 215
                },
                {
                    "start_date": "2015-04-03T04:00:00+02:00",
                    "end_date": "2015-04-03T05:00:00+02:00",
                    "value": 218
                },
                {
                    "start_date": "2015-04-03T05:00:00+02:00",
                    "end_date": "2015-04-03T06:00:00+02:00",
                    "value": 213
                },
                {
                    "start_date": "2015-04-03T06:00:00+02:00",
                    "end_date": "2015-04-03T07:00:00+02:00",
                    "value": 215
                },
                {
                    "start_date": "2015-04-03T07:00:00+02:00",
                    "end_date": "2015-04-03T08:00:00+02:00",
                    "value": 214
                },
                {
                    "start_date": "2015-04-03T08:00:00+02:00",
                    "end_date": "2015-04-03T09:00:00+02:00",
                    "value": 215
                },
                {
                    "start_date": "2015-04-03T09:00:00+02:00",
                    "end_date": "2015-04-03T10:00:00+02:00",
                    "value": 211
                },
                {
                    "start_date": "2015-04-03T10:00:00+02:00",
                    "end_date": "2015-04-03T11:00:00+02:00",
                    "value": 207
                },
                {
                    "start_date": "2015-04-03T11:00:00+02:00",
                    "end_date": "2015-04-03T12:00:00+02:00",
                    "value": 207
                },
                {
                    "start_date": "2015-04-03T12:00:00+02:00",
                    "end_date": "2015-04-03T13:00:00+02:00",
                    "value": 209
                },
                {
                    "start_date": "2015-04-03T13:00:00+02:00",
                    "end_date": "2015-04-03T14:00:00+02:00",
                    "value": 206
                },
                {
                    "start_date": "2015-04-03T14:00:00+02:00",
                    "end_date": "2015-04-03T15:00:00+02:00",
                    "value": 204
                },
                {
                    "start_date": "2015-04-03T15:00:00+02:00",
                    "end_date": "2015-04-03T16:00:00+02:00",
                    "value": 206
                },
                {
                    "start_date": "2015-04-03T16:00:00+02:00",
                    "end_date": "2015-04-03T17:00:00+02:00",
                    "value": 207
                },
                {
                    "start_date": "2015-04-03T17:00:00+02:00",
                    "end_date": "2015-04-03T18:00:00+02:00",
                    "value": 205
                },
                {
                    "start_date": "2015-04-03T18:00:00+02:00",
                    "end_date": "2015-04-03T19:00:00+02:00",
                    "value": 203
                },
                {
                    "start_date": "2015-04-03T19:00:00+02:00",
                    "end_date": "2015-04-03T20:00:00+02:00",
                    "value": 202
                },
                {
                    "start_date": "2015-04-03T20:00:00+02:00",
                    "end_date": "2015-04-03T21:00:00+02:00",
                    "value": 195
                },
                {
                    "start_date": "2015-04-03T21:00:00+02:00",
                    "end_date": "2015-04-03T22:00:00+02:00",
                    "value": 197
                },
                {
                    "start_date": "2015-04-03T22:00:00+02:00",
                    "end_date": "2015-04-03T23:00:00+02:00",
                    "value": 201
                },
                {
                    "start_date": "2015-04-03T23:00:00+02:00",
                    "end_date": "2015-04-04T00:00:00+02:00",
                    "value": 202
                }
            ]
        },
        {
            "start_date": "2015-04-03T00:00:00+02:00",
            "end_date": "2015-04-04T00:00:00+02:00",
            "production_type": "WIND_ONSHORE",
            "values": [
                {
                    "start_date": "2015-04-03T00:00:00+02:00",
                    "end_date": "2015-04-03T01:00:00+02:00",
                    "value": 1017
                },
                {
                    "start_date": "2015-04-03T01:00:00+02:00",
                    "end_date": "2015-04-03T02:00:00+02:00",
                    "value": 1027
                },
                {
                    "start_date": "2015-04-03T02:00:00+02:00",
                    "end_date": "2015-04-03T03:00:00+02:00",
                    "value": 1017
                },
                {
                    "start_date": "2015-04-03T03:00:00+02:00",
                    "end_date": "2015-04-03T04:00:00+02:00",
                    "value": 1056
                },
                {
                    "start_date": "2015-04-03T04:00:00+02:00",
                    "end_date": "2015-04-03T05:00:00+02:00",
                    "value": 1066
                },
                {
                    "start_date": "2015-04-03T05:00:00+02:00",
                    "end_date": "2015-04-03T06:00:00+02:00",
                    "value": 1105
                },
                {
                    "start_date": "2015-04-03T06:00:00+02:00",
                    "end_date": "2015-04-03T07:00:00+02:00",
                    "value": 1134
                },
                {
                    "start_date": "2015-04-03T07:00:00+02:00",
                    "end_date": "2015-04-03T08:00:00+02:00",
                    "value": 1238
                },
                {
                    "start_date": "2015-04-03T08:00:00+02:00",
                    "end_date": "2015-04-03T09:00:00+02:00",
                    "value": 1295
                },
                {
                    "start_date": "2015-04-03T09:00:00+02:00",
                    "end_date": "2015-04-03T10:00:00+02:00",
                    "value": 1327
                },
                {
                    "start_date": "2015-04-03T10:00:00+02:00",
                    "end_date": "2015-04-03T11:00:00+02:00",
                    "value": 1170
                },
                {
                    "start_date": "2015-04-03T11:00:00+02:00",
                    "end_date": "2015-04-03T12:00:00+02:00",
                    "value": 1209
                },
                {
                    "start_date": "2015-04-03T12:00:00+02:00",
                    "end_date": "2015-04-03T13:00:00+02:00",
                    "value": 1275
                },
                {
                    "start_date": "2015-04-03T13:00:00+02:00",
                    "end_date": "2015-04-03T14:00:00+02:00",
                    "value": 1357
                },
                {
                    "start_date": "2015-04-03T14:00:00+02:00",
                    "end_date": "2015-04-03T15:00:00+02:00",
                    "value": 1309
                },
                {
                    "start_date": "2015-04-03T15:00:00+02:00",
                    "end_date": "2015-04-03T16:00:00+02:00",
                    "value": 1346
                },
                {
                    "start_date": "2015-04-03T16:00:00+02:00",
                    "end_date": "2015-04-03T17:00:00+02:00",
                    "value": 1379
                },
                {
                    "start_date": "2015-04-03T17:00:00+02:00",
                    "end_date": "2015-04-03T18:00:00+02:00",
                    "value": 1399
                },
                {
                    "start_date": "2015-04-03T18:00:00+02:00",
                    "end_date": "2015-04-03T19:00:00+02:00",
                    "value": 1398
                },
                {
                    "start_date": "2015-04-03T19:00:00+02:00",
                    "end_date": "2015-04-03T20:00:00+02:00",
                    "value": 1379
                },
                {
                    "start_date": "2015-04-03T20:00:00+02:00",
                    "end_date": "2015-04-03T21:00:00+02:00",
                    "value": 1326
                },
                {
                    "start_date": "2015-04-03T21:00:00+02:00",
                    "end_date": "2015-04-03T22:00:00+02:00",
                    "value": 1315
                },
                {
                    "start_date": "2015-04-03T22:00:00+02:00",
                    "end_date": "2015-04-03T23:00:00+02:00",
                    "value": 1177
                },
                {
                    "start_date": "2015-04-03T23:00:00+02:00",
                    "end_date": "2015-04-04T00:00:00+02:00",
                    "value": 1146
                }
            ]
        },
        {
            "start_date": "2015-04-03T00:00:00+02:00",
            "end_date": "2015-04-04T00:00:00+02:00",
            "production_type": "TOTAL",
            "values": [
                {
                    "start_date": "2015-04-03T00:00:00+02:00",
                    "end_date": "2015-04-03T01:00:00+02:00",
                    "value": 60454
                },
                {
                    "start_date": "2015-04-03T01:00:00+02:00",
                    "end_date": "2015-04-03T02:00:00+02:00",
                    "value": 57874
                },
                {
                    "start_date": "2015-04-03T02:00:00+02:00",
                    "end_date": "2015-04-03T03:00:00+02:00",
                    "value": 56485
                },
                {
                    "start_date": "2015-04-03T03:00:00+02:00",
                    "end_date": "2015-04-03T04:00:00+02:00",
                    "value": 55024
                },
                {
                    "start_date": "2015-04-03T04:00:00+02:00",
                    "end_date": "2015-04-03T05:00:00+02:00",
                    "value": 54892
                },
                {
                    "start_date": "2015-04-03T05:00:00+02:00",
                    "end_date": "2015-04-03T06:00:00+02:00",
                    "value": 55313
                },
                {
                    "start_date": "2015-04-03T06:00:00+02:00",
                    "end_date": "2015-04-03T07:00:00+02:00",
                    "value": 58021
                },
                {
                    "start_date": "2015-04-03T07:00:00+02:00",
                    "end_date": "2015-04-03T08:00:00+02:00",
                    "value": 62755
                },
                {
                    "start_date": "2015-04-03T08:00:00+02:00",
                    "end_date": "2015-04-03T09:00:00+02:00",
                    "value": 64074
                },
                {
                    "start_date": "2015-04-03T09:00:00+02:00",
                    "end_date": "2015-04-03T10:00:00+02:00",
                    "value": 65256
                },
                {
                    "start_date": "2015-04-03T10:00:00+02:00",
                    "end_date": "2015-04-03T11:00:00+02:00",
                    "value": 65136
                },
                {
                    "start_date": "2015-04-03T11:00:00+02:00",
                    "end_date": "2015-04-03T12:00:00+02:00",
                    "value": 65559
                },
                {
                    "start_date": "2015-04-03T12:00:00+02:00",
                    "end_date": "2015-04-03T13:00:00+02:00",
                    "value": 65518
                },
                {
                    "start_date": "2015-04-03T13:00:00+02:00",
                    "end_date": "2015-04-03T14:00:00+02:00",
                    "value": 64528
                },
                {
                    "start_date": "2015-04-03T14:00:00+02:00",
                    "end_date": "2015-04-03T15:00:00+02:00",
                    "value": 63313
                },
                {
                    "start_date": "2015-04-03T15:00:00+02:00",
                    "end_date": "2015-04-03T16:00:00+02:00",
                    "value": 62400
                },
                {
                    "start_date": "2015-04-03T16:00:00+02:00",
                    "end_date": "2015-04-03T17:00:00+02:00",
                    "value": 61370
                },
                {
                    "start_date": "2015-04-03T17:00:00+02:00",
                    "end_date": "2015-04-03T18:00:00+02:00",
                    "value": 61507
                },
                {
                    "start_date": "2015-04-03T18:00:00+02:00",
                    "end_date": "2015-04-03T19:00:00+02:00",
                    "value": 62538
                },
                {
                    "start_date": "2015-04-03T19:00:00+02:00",
                    "end_date": "2015-04-03T20:00:00+02:00",
                    "value": 63045
                },
                {
                    "start_date": "2015-04-03T20:00:00+02:00",
                    "end_date": "2015-04-03T21:00:00+02:00",
                    "value": 62374
                },
                {
                    "start_date": "2015-04-03T21:00:00+02:00",
                    "end_date": "2015-04-03T22:00:00+02:00",
                    "value": 60865
                },
                {
                    "start_date": "2015-04-03T22:00:00+02:00",
                    "end_date": "2015-04-03T23:00:00+02:00",
                    "value": 59864
                },
                {
                    "start_date": "2015-04-03T23:00:00+02:00",
                    "end_date": "2015-04-04T00:00:00+02:00",
                    "value": 60474
                }
            ]
        }
    ]
}